[
    {
        "name": "8-Bit",
        "className": "onePointOne",
        "id": "wk6o4mpk",
        "vars": [
            [
                "kn046m0l",
                "klr7j6mq"
            ],
            [
                "ql6gxqk8",
                "jqz4924l"
            ]
        ]
    },
    {
        "name": "Linear",
        "className": "legacy",
        "id": "rkljyx8d",
        "vars": [
            [
                "ylq9r0v8",
                "z19r8pk1"
            ],
            [
                "wl365ryl",
                "5lmnp30q"
            ]
        ]
    },
    {
        "name": "Any%",
        "className": "nmg",
        "id": "5dw8x00d",
        "vars": [
            [
                "6njvwz5n",
                "gq7g9zdq"
            ],
            [
                "wle6zm28",
                "zqon9e4l"
            ]
        ]
    },
    {
        "name": "100%",
        "className": "dlc",
        "id": "q257w0gd",
        "vars": [
            [
                "ql6g51w8",
                "5q8z2r3q"
            ]
        ]
    },
    {
        "name": "Picnic Panic DLC",
        "className": "dlcbase",
        "id": "xd1lpp7k",
        "vars": [
            [
                "r8ropo78",
                "jqzx5om1"
            ],
            [
                "5ly7479l",
                "21d3y0jq"
            ]
        ]
    }
]